Metadata-Version: 2.1
Name: NumBase
Version: 0.2
Summary: Arithmetic operations of numbers with different number systems
Home-page: UNKNOWN
Author: lemme-hype
Author-email: terekhova.kris98@gmail.com
License: Apache Lecense, Version 2.0, see Lecense file
Platform: UNKNOWN
Requires-Python: >=3.6
